marshmallow_pyfields/__init__.py
marshmallow_pyfields/_version.py
marshmallow_pyfields/main.py
marshmallow_pyfields-0.5.1.dist-info/LICENSE
marshmallow_pyfields-0.5.1.dist-info/METADATA
marshmallow_pyfields-0.5.1.dist-info/WHEEL
marshmallow_pyfields-0.5.1.dist-info/top_level.txt
marshmallow_pyfields-0.5.1.dist-info/RECORD
