Metadata-Version: 2.1
Name: marshmallow-pyfields
Version: 0.5.1
Summary: Automatic generation of `marshmallow` schemas from classes using `pyfields`.
Home-page: https://github.com/smarie/python-marshmallow-pyfields
Author: Sylvain MARIE
Author-email: sylvain.marie@se.com
License: BSD 3-Clause
Download-URL: https://github.com/smarie/python-marshmallow-pyfields/tarball/0.5.1
Keywords: marshmallow pyfields field class serialization rest json api marshal marshalling deserialization validation schema
Platform: UNKNOWN
Classifier: Development Status :: 5 - Production/Stable
Classifier: Intended Audience :: Developers
Classifier: License :: OSI Approved :: BSD License
Classifier: Topic :: Software Development :: Libraries :: Python Modules
Classifier: Programming Language :: Python
Classifier: Programming Language :: Python :: 3.6
Classifier: Programming Language :: Python :: 3.7
Classifier: Programming Language :: Python :: 3.8
Requires-Dist: pyfields
Requires-Dist: marshmallow
Requires-Dist: marshmallow-dataclass
